cwldep/__init__.py
cwldep-1.0.dist-info/METADATA
cwldep-1.0.dist-info/RECORD
cwldep-1.0.dist-info/WHEEL
cwldep-1.0.dist-info/entry_points.txt
cwldep-1.0.dist-info/top_level.txt
cwldep-1.0.dist-info/zip-safe
