Metadata-Version: 2.1
Name: cwldep
Version: 1.0
Summary: Common workflow language dependency manager
Home-page: https://github.com/common-workflow-language/cwldep
Author: Common workflow language working group
Author-email: common-workflow-language@googlegroups.com
License: Apache 2.0
Download-URL: https://github.com/common-workflow-language/cwldep
Platform: UNKNOWN
Requires-Python: >=2.7, !=3.0.*, !=3.1.*, !=3.2.*, !=3.3.*, <4
Requires-Dist: cwltool
Requires-Dist: python-dateutil
